bcon/__init__.py
bcon/compress.py
bcon/funcs.py
bcon/pack.py
bcon-0.0.2.dist-info/LICENSE
bcon-0.0.2.dist-info/METADATA
bcon-0.0.2.dist-info/WHEEL
bcon-0.0.2.dist-info/top_level.txt
bcon-0.0.2.dist-info/RECORD
